{
    "name": "n8n-nodes-firstpromoter",
    "nodeVersion": "1.0",
    "codexVersion": "1.0",
    "categories": ["Marketing & Content","Sales", "Productivity", "Analytics" ],
    "resources": {
        "credentialDocumentation": [
            {
                "url": "https://docs.firstpromoter.com/api-reference-v2/api-admin/authentication"
            }
        ],
        "primaryDocumentation": [
            {
                "url": "https://docs.firstpromoter.com/api-reference-v2/api-admin/introduction"
            }
        ]
    },
    "alias": ["FirstPromoter v2","FirstPromoter v2 API", "FirstPromoter API"]
}
